{
    "Badge-Parameter-Color": {
        "prefix": [
            "Badge Parameter Color",
            "bpc"
        ],
        "body": [
            "color=${1|BrightGreen,Green,YellowGreen,Yellow,Orange,Red,Blue,LightGrey,success,important,critical,infomational,inactive,blueviolet,ff69b4,9cf|}$0"
        ],
        "decription": "Badge-Parameter-Color"
    },
    "Badge-Parameter-Style": {
        "prefix": [
            "Badge Parameter Style",
            "bps"
        ],
        "body": [
            "style=${1|flat,flat-square,plastic,for-the-badge,social|}$0"
        ],
        "decription": "Badge Parameter Style"
    },
    "Badge-Parameter-Logo": {
        "prefix": [
            "Badge Parameter Logo",
            "bpl"
        ],
        "body": [
            "logo=${1|Gatsby,Scaleway,Adobe-After-Effects,KaiOS,Tor,Podcasts,Bit,Adobe-Premiere,JustGiving,GOG.com,Slack,Microsoft-OneNote,Lyft,Adobe-XD,Player.me,GraphQL,Sass,T-Mobile,Aurelia,Adobe-InDesign,Codecov,Disroot,Dribbble,Gitter,ProcessWire,Raspberry-Pi,Songkick,Foursquare,InVision,Common-Workflow-Language,Angular,Slides,Apache-Flink,CSS-Wizardry,Instagram,Debian,The-Mighty,Meetup,Stadia,Autotask,Pocket,Pinterest,Jest,Sina-Weibo,MasterCard,Twilio,GNU-social,Opera,Macy’s,Nintendo-Switch,Livestream,Redbubble,Apache,MEGA,Netflix,Tencent-QQ,Airbnb,Microsoft-Access,CakePHP,Verizon,Toggl,eBay,Server-Fault,AMD,Bitdefender,Trakt,WireGuard,Turkish-Airlines,Gulp,Adobe,DTube,Huawei,Kirby,Microgenetics,Yandex,YouTube,Tinder,Archive-of-Our-Own,Weasyl,NPM,FileZilla,Humble-Bundle,Quantopian,Jabber,Jekyll,Rails,Tesla,Yelp,Meteor,Adobe-Creative-Cloud,Flipboard,TrainerRoad,Udemy,Ko-fi,Ansible,Red-Hat,Itch.io,Oracle,GNU,FreeBSD,Codewars,Quora,Ruby,Scala,Last.fm,Plurk,Redis,Sauce-Labs,MakerBot,TED,rollup.js,Todoist,Wolfram,Wolfram-Language,Wolfram-Mathematica,ReverbNation,jsDelivr,SparkFun,BuzzFeed,Reason,Jenkins,Gmail,Laravel,Patreon,Everplaces,AddThis,GitLab,RubyGems,Adobe-Acrobat-Reader,Sentry,Eventbrite,Git,CodeIgniter,Bower,SoundCloud,HubSpot,Microsoft-PowerPoint,Brave,Product-Hunt,DuckDuckGo,HTML5,Highly,Blogger,Smashing-Magazine,Figma,Postman,Ubuntu,Auth0,Pluralsight,Reddit,Kentico,Swift,Zapier,Y-Combinator,Klout,Magento,Bitly,Origin,SparkPost,Sogou,Strava,FACEIT,Etsy,Buy-Me-A-Coffee,devRant,Discover,Jupyter,Blender,Draugiem.lv,Monero,OCaml,Crunchyroll,Odnoklassniki,Elsevier,Mix,Twoo,Stack-Overflow,Composer,Grafana,Fandango,OpenVPN,Cloudflare,Viadeo,Overcast,Adobe-Illustrator,Proxmox,Haxe,SlickPic,Goodreads,Open-Access,Micro.blog,TYPO3,VLC-media-player,Boost,Wattpad,D3.js,Creative-Commons,Bitcoin,Swarm,Audible,Wix,Mozilla-Firefox,Chef,Amazon,LeetCode,Fur-Affinity,RSS,Monogram,Prettier,Fido-Alliance,Plex,Google-Allo,Fnac,GoldenLine,Google-Keep,Untappd,Google-Analytics,Monkey-tie,Firebase,JET,Linux,DocuSign,IMDb,Launchpad,AlloCiné,Sprint,Liberapay,Spreaker,Qzone,Tapas,Qwiklabs,Shell,Babel,Pantheon,MailChimp,JavaScript,Pingdom,Snapchat,DAZN,Khan-Academy,Android,ORCID,ICQ,NVIDIA,Kik,WeChat,Envato,Adobe-Typekit,Zerply,openSUSE,Linux-Mint,Groupon,Houzz,Trulia,Qiita,CiviCRM,Sensu,Shopify,Gumtree,Empire-Kred,Nodemon,Upwork,Adobe-Dreamweaver,When-I-Work,Instacart,OpenStreetMap,Event-Store,freeCodeCamp,Xbox,Node.js,MongoDB,Hulu,Line,Basecamp,NGINX,Feedly,Letterboxd,Evernote,Manjaro,Treehouse,Glassdoor,Vim,Sellfy,DeviantArt,Cash-App,HackerRank,WhatsApp,Spotify,Nextdoor,Kickstarter,Microsoft-Excel,ESEA,Picarto.TV,Graphcool,LINE-WEBTOON,homify,Snapcraft,Speaker-Deck,Koding,Gauges,Google-Hangouts,Vue.js,Geocaching,Castro,The-Movie-Database,Greenkeeper,Moo,Skyliner,Vine,Nuxt.js,TripAdvisor,Steemit,Adobe-Audition,About.me,Bing,Google-Hangouts-Chat,Magisk,Netlify,HERE,Slashdot,Pingup,Xing,Adobe-Lightroom-CC,Umbraco,Canva,Travis-CI,Gumroad,Arduino,Fitbit,Exercism,Runkeeper,WP-Engine,HackHands,Angular-Universal,Zendesk,Electron,Dashlane,Probot,Deezer,CloudBees,Proto.io,AppVeyor,Adobe-Photoshop,Go,Bandcamp,Minutemailer,Udacity,Zorin,React,Java,Tencent-Weibo,Beats,Elastic,Elastic-Cloud,Elasticsearch,Elastic-Stack,Kibana,Logstash,X-Pack,Cassandra,Periscope,AT&T,Kodi,Co-op,Vimeo,Xero,LiveJournal,Sourcegraph,F-Secure,Hatena-Bookmark,Bath-ASU,Experts-Exchange,Skype,Kaggle,SitePoint,Neo4j,CEVO,Salesforce,ArtStation,ComproPago,Messenger,Ghost,Helm,Mathworks,Yarn,Topcoder,webcomponents.org,Gitpod,HockeyApp,EVRY,WordPress,Gravatar,Dell,Kotlin,Virb,Telegram,Super-User,Aventrix,Clockify,Dependabot,LinkedIn,Arch-Linux,Sega,SAP,XSplit,Teespring,500px,Webpack,OSMC,Google-Play,Pandora,Garmin,Docker,ACM,Nextcloud,Crunchbase,Microsoft-Azure,Linux-Foundation,IconJar,Hackster,SPDX,Trello,Adobe-Lightroom-Classic,Stripe,Brand.ai,Dassault-Systèmes,Drupal,Codeforces,Hexo,Twitter,Iata,SpaceX,KeyCDN,Scribd,Venmo,TypeScript,Visual-Studio-Code,Storify,PlanGrid,TeamViewer,MediaFire,Codecademy,jQuery,CSS3,Microsoft-Outlook,Yammer,Read-the-Docs,NuGet,C++,GOV.UK,Godot-Engine,Intel,Chase,Azure-DevOps,Castorama,Microsoft-Edge,Windows,Octopus-Deploy,Mail.Ru,Buffer,StackShare,Dynatrace,elementary,PayPal,MySQL,CMake,PyPI,Flutter,Coderwall,Renren,iFixit,Internet-Explorer,Signal,UIkit,Shazam,Disqus,Keybase,Pivotal-Tracker,PostgreSQL,JSFiddle,Python,Furry-Network,Joomla,Mastodon,Riot,Intercom,Steem,Let’s-Encrypt,American-Express,Laravel-Horizon,DigitalOcean,Delicious,OVH,dblp,Zillow,iCloud,deepin,ARAL,Riseup,Buddy,StubHub,R,Lanyrd,Dailymotion,Campaign-Monitor,VK,Stack-Exchange,Coursera,Solus,Flickr,Mixcloud,Facebook,Mixer,Toptal,Xcode,Tumblr,Microsoft-Word,Atlassian,Bamboo,Bitbucket,HipChat,Designer-News,Dropbox,Confluence,Jira,Opsgenie,Statuspage,PlayStation,PlayStation-3,PlayStation-4,Subversion,Microsoft-OneDrive,V8,Ionic,Google,Google-Chrome,Google-Cloud,Google-Drive,Google-Podcasts,Behance,PowerShell,Framer,Vagrant,Fedora,Clojure,Azure-Pipelines,Kubernetes,Boeing,Codio,Hashnode,Realm,Discord,Qualcomm,NativeScript,Visa,Samsung,Samsung-Pay,Roots,Prismic,PHP,Lua,Pinboard,ProtonMail,Baidu,Snyk,Nucleo,Viber,Nintendo-GameCube,ESLint,Spotlight,Marketo,Eclipse-IDE,Haskell,Favro,Twitch,Redux,Bootstrap,Heroku,Spacemacs,Circle,Yahoo!,.NET,Tails,LGTM,Gerrit,Synology,FeatHub,Apple,Scrutinizer-CI,Nintendo,Wii-U,Wii,Automatic,Material-Design,Microsoft,Google-Pay,Atom,SourceForge,Conekta,Codeship,HackerEarth,Ethereum,Asana,Stylus,Known,CircleCI,Unreal-Engine,Statamic,Epic-Games,Amazon-AWS,CoffeeScript,Monzo,Codacy,Sublime-Text,Quantcast,Matternet,StyleShare,Pagekit,Grav,Drone,Cirrus-CI,Big-Cartel,Oculus,LibraryThing,Instapaper,Django,Hackaday,GitHub,Simple-Icons,Medium,dev.to,Myspace,Zeit,Wire,Wikipedia,WebStorm,VSCO,Unsplash,Unity,Ubisoft,Uber,Tik-Tok,Tidal,Symfony,Stitcher,Steam,Staticman,Squarespace,Socket.io,Society6,Safari,Rust,Next.js,MX-Linux,Mozilla,MediaTemple,Matrix,Markdown,JSON,IntelliJ-IDEA,Inkscape,Hootsuite,Flattr,Flask,Ello,Discourse,Digg,Diaspora,Deno,Conda-Forge,CodeSandbox,CodePen,Code-Climate,Apple-Pay,Apple-Music,AngelList|}$0"
        ],
        "decription": "Badge-Parameter-Logo"
    }
}